rosagents/__init__.py
rosagents/agents.py
rosagents/default_tools.py
rosagents/e2b_executor.py
rosagents/gradio_ui.py
rosagents/local_python_executor.py
rosagents/models.py
rosagents/monitoring.py
rosagents/prompts.py
rosagents/tool_validation.py
rosagents/tools.py
rosagents/types.py
rosagents/utils.py
rosagents-0.0.1.dist-info/LICENSE
rosagents-0.0.1.dist-info/METADATA
rosagents-0.0.1.dist-info/WHEEL
rosagents-0.0.1.dist-info/top_level.txt
rosagents-0.0.1.dist-info/RECORD
